jupyterhub_nomad_spawner/__init__.py
jupyterhub_nomad_spawner/consul/consul_service.py
jupyterhub_nomad_spawner/job_factory.py
jupyterhub_nomad_spawner/job_options_factory.py
jupyterhub_nomad_spawner/nomad/__init__.py
jupyterhub_nomad_spawner/nomad/nomad_model.py
jupyterhub_nomad_spawner/nomad/nomad_service.py
jupyterhub_nomad_spawner/spawner.py
jupyterhub_nomad_spawner/templates/form.html.j2
jupyterhub_nomad_spawner/templates/job.hcl.j2
jupyterhub_nomad_spawner-0.3.0.dist-info/LICENSE
jupyterhub_nomad_spawner-0.3.0.dist-info/METADATA
jupyterhub_nomad_spawner-0.3.0.dist-info/WHEEL
jupyterhub_nomad_spawner-0.3.0.dist-info/entry_points.txt
jupyterhub_nomad_spawner-0.3.0.dist-info/RECORD
