Metadata-Version: 2.1
Name: jupyterhub-nomad-spawner
Version: 0.3.0
Summary: A JupyterHub Spawner that launches isolated notebooks as job
Author: Max Fröhlich
Author-email: maxbruchmann@gmail.com
Requires-Python: >=3.10,<3.11
Classifier: Programming Language :: Python :: 3
Classifier: Programming Language :: Python :: 3.10
Requires-Dist: Jinja2 (>=3.1.2,<4.0.0)
Requires-Dist: attrs (>=23.1.0,<24.0.0)
Requires-Dist: httpx (>=0.24.0,<0.25.0)
Requires-Dist: jupyterhub (>=4.0.1,<5.0.0)
Requires-Dist: pydantic (>=1.9.0,<2.0.0)
Requires-Dist: tenacity (>=8.0.1,<9.0.0)
Requires-Dist: traitlets (>=5.1.1,<6.0.0)
